LICENSE.txt
MANIFEST.in
README.md
setup.py
WebSiteCloner/HTTPLogger.py
WebSiteCloner/WebSiteCloner.py
WebSiteCloner/__init__.py
WebSiteCloner/__main__.py
WebSiteCloner.egg-info/PKG-INFO
WebSiteCloner.egg-info/SOURCES.txt
WebSiteCloner.egg-info/dependency_links.txt
WebSiteCloner.egg-info/entry_points.txt
WebSiteCloner.egg-info/top_level.txt