Metadata-Version: 2.1
Name: WebSiteCloner
Version: 0.0.1
Summary: This package implement a Web Site Cloner and his HTTP server to launch it.
Home-page: https://github.com/mauricelambert/WebSiteCloner
Author: Maurice Lambert
Author-email: mauricelambert434@gmail.com
License: UNKNOWN
Platform: UNKNOWN
Classifier: Programming Language :: Python
Classifier: Development Status :: 5 - Production/Stable
Classifier: Environment :: Console
Classifier: Natural Language :: English
Classifier: Operating System :: OS Independent
Classifier: Programming Language :: Python :: 3.8
Requires-Python: >=3.6
